davinci_mcp/__init__.py
davinci_mcp/cli.py
davinci_mcp/resolve_client.py
davinci_mcp/resolve_client_mock.py
davinci_mcp/server.py
davinci_mcp/server_mock.py
davinci_mcp/types.py
davinci_mcp/resources/__init__.py
davinci_mcp/tools/__init__.py
davinci_mcp/utils/__init__.py
davinci_mcp/utils/platform.py
iflow_mcp_positronikal_davinci_mcp_professional-2.2.1.dist-info/METADATA
iflow_mcp_positronikal_davinci_mcp_professional-2.2.1.dist-info/WHEEL
iflow_mcp_positronikal_davinci_mcp_professional-2.2.1.dist-info/entry_points.txt
iflow_mcp_positronikal_davinci_mcp_professional-2.2.1.dist-info/licenses/AUTHORS.md
iflow_mcp_positronikal_davinci_mcp_professional-2.2.1.dist-info/licenses/COPYING.md
iflow_mcp_positronikal_davinci_mcp_professional-2.2.1.dist-info/RECORD
