Metadata-Version: 2.4
Name: iflow-mcp-positronikal-davinci-mcp-professional
Version: 2.2.1
Summary: Model Context Protocol server for DaVinci Resolve integration
Project-URL: Homepage, https://github.com/Positronikal/davinci-mcp-professional
Project-URL: Repository, https://github.com/Positronikal/davinci-mcp-professional
Project-URL: Issues, https://github.com/Positronikal/davinci-mcp-professional/issues
Author-email: Hoyt Harness <hoyt.harness@gmail.com>
License: MIT
License-File: AUTHORS.md
License-File: COPYING.md
Classifier: Development Status :: 4 - Beta
Classifier: Intended Audience :: Developers
Classifier: License :: OSI Approved :: MIT License
Classifier: Programming Language :: Python :: 3.9
Classifier: Programming Language :: Python :: 3.10
Classifier: Programming Language :: Python :: 3.11
Classifier: Programming Language :: Python :: 3.12
Requires-Python: >=3.9
Requires-Dist: anyio>=4.0.0
Requires-Dist: click>=8.0.0
Requires-Dist: colorama>=0.4.6
Requires-Dist: httpx>=0.25.0
Requires-Dist: mcp>=1.0.0
Requires-Dist: pydantic>=2.0.0
Provides-Extra: dev
Requires-Dist: black>=23.0.0; extra == 'dev'
Requires-Dist: isort>=5.12.0; extra == 'dev'
Requires-Dist: mypy>=1.5.0; extra == 'dev'
Requires-Dist: pytest-asyncio>=0.21.0; extra == 'dev'
Requires-Dist: pytest-cov>=4.0.0; extra == 'dev'
Requires-Dist: pytest>=7.0.0; extra == 'dev'
Requires-Dist: ruff>=0.1.0; extra == 'dev'
Provides-Extra: security
Requires-Dist: bandit>=1.7.5; extra == 'security'
Requires-Dist: pip-licenses>=4.3.0; extra == 'security'
Requires-Dist: safety>=2.3.0; extra == 'security'
Requires-Dist: semgrep>=1.45.0; extra == 'security'
